{
  "name": "Cauldron",
  "nativeApps": [
    {
      "name": "EndeavorAndroidNativeApp",
      "platforms": [
        {
          "name": "android",
          "versions": [
            {
              "name": "0.0.1",
              "codePush": {},
              "container": {
                "jsApiImpls": [],
                "miniApps": [
                  "git+ssh://git@github.com/amandalragone/endeavorminiapp.git#1.0.8"
                ],
                "nativeDeps": [
                  "ernnavigation-api-impl-native@2.1.0",
                  "ernnavigation-api@2.1.0",
                  "react-native-electrode-bridge@1.6.0",
                  "react-native@0.68.7"
                ],
                "ernVersion": "0.51.0"
              },
              "isReleased": false,
              "nativeDeps": [],
              "yarnLocks": {
                "container": "8a1a33eb-702a-4cc2-8f04-49a44cf24008"
              },
              "containerVersion": "1.0.0"
            }
          ]
        }
      ]
    }
  ],
  "schemaVersion": "3.0.0"
}
